{
  "lp_contract": "KaglaTokenV3",
  "pool_types": ["arate"],
  "wrapped_contract": "ATokenMock",
  "swap_address": "0xAdA48a0F05bc8e852A3577d7fCa25C8E97075a08",
  "lp_token_address": "0x626CD15023bFE79e44E3721Fe53361B924EC0373",
  "gauge_addresses": ["0x01826dE23E80200595D2dE01B8c17a8e76BaB2df"],
  "lp_constructor": {
    "symbol": "a3KGL",
    "name": "Kagla.fi lDAI/lUSDC/lUSDT"
  },
  "swap_constructor": {
    "_A": 200,
    "_fee": 4000000,
    "_admin_fee": 5000000000,
    "_offpeg_fee_multiplier": 20000000000,
    "_aave_lending_pool": "0x8022327a333eAeFaD46A723CDcA1aeFdA12afA53"
  },
  "coins": [
    {
      "name": "lDAI",
      "underlying_name": "DAI",
      "decimals": 18,
      "wrapped_decimals": 18,
      "tethered": false,
      "underlying_address": "0x257f1a047948f73158DaDd03eB84b34498bCDc60",
      "wrapped_address": "0x59448269aa5Cb875F27268368bB1913bF60580aD"
    },
    {
      "name": "lUSDC",
      "underlying_name": "USDC",
      "decimals": 6,
      "wrapped_decimals": 6,
      "tethered": false,
      "underlying_address": "0x458db3bEf6ffC5212f9359bbDAeD0D5A58129397",
      "wrapped_address": "0xF4D80e698D40Aae4F8486E59D3A52BB4b637e867"
    },
    {
      "name": "lUSDT",
      "underlying_name": "USDT",
      "decimals": 6,
      "wrapped_decimals": 6,
      "tethered": false,
      "underlying_address": "0xdB25FDCCe3E63B376D308dC2D46234632d9959d8",
      "wrapped_address": "0xFa668E06fe382ECb6ADBad15108357c1125aF906"
    }
  ]
}
